{
  "annotations": { "list": [] },
  "editable": true,
  "gnetId": null,
  "id": null,
  "panels": [
    {
      "datasource": "Prometheus",
      "gridPos": { "h": 8, "w": 8, "x": 0, "y": 0 },
      "id": 1,
      "targets": [
        {
          "expr": "sum(rate(http_server_requests_seconds_count{service=\"$service\"}[1m]))",
          "legendFormat": "RPS",
          "refId": "A"
        }
      ],
      "title": "Request Rate (RPS)",
      "type": "timeseries"
    },
    {
      "datasource": "Prometheus",
      "fieldConfig": { "defaults": { "unit": "percent", "color": { "mode": "thresholds" } } },
      "gridPos": { "h": 8, "w": 8, "x": 8, "y": 0 },
      "id": 2,
      "targets": [
        {
          "expr": "(sum(rate(http_server_requests_seconds_count{service=\"$service\", status=~\"5..\"}[1m])) / sum(rate(http_server_requests_seconds_count{service=\"$service\"}[1m]))) * 100",
          "legendFormat": "Error %",
          "refId": "A"
        }
      ],
      "title": "Error Rate (%)",
      "type": "timeseries"
    },
    {
      "datasource": "Prometheus",
      "fieldConfig": { "defaults": { "unit": "s" } },
      "gridPos": { "h": 8, "w": 8, "x": 16, "y": 0 },
      "id": 3,
      "targets": [
        {
          "expr": "histogram_quantile(0.95, sum(rate(http_server_requests_seconds_bucket{service=\"$service\"}[1m])) by (le))",
          "legendFormat": "P95 Latency",
          "refId": "A"
        }
      ],
      "title": "Duration (P95 Latency)",
      "type": "timeseries"
    },
    {
      "datasource": "Prometheus",
      "gridPos": { "h": 8, "w": 12, "x": 0, "y": 8 },
      "id": 4,
      "targets": [
        {
          "expr": "sum(hikaricp_connections_active{service=\"$service\"})",
          "legendFormat": "Active Connections",
          "refId": "A"
        }
      ],
      "title": "DB Connection Pool (HikariCP)",
      "type": "timeseries"
    }
  ],
  "schemaVersion": 38,
  "tags": ["L2", "Service"],
  "templating": {
    "list": [
      {
        "current": {},
        "datasource": "Prometheus",
        "definition": "label_values(http_server_requests_seconds_count, service)",
        "hide": 0,
        "includeAll": false,
        "multi": false,
        "name": "service",
        "options": [],
        "query": "label_values(http_server_requests_seconds_count, service)",
        "refresh": 1,
        "regex": "",
        "skipUrlSync": false,
        "sort": 1,
        "type": "query"
      }
    ]
  },
  "time": { "from": "now-30m", "to": "now" },
  "title": "Level 2 - Service RED Dashboard",
  "uid": "l2-service-view",
  "version": 1
}